{
  "title": "Cómo los desarrolladores pueden crear logos efectivos para sus proyectos personales",
  "meta_description": "Aprende cómo diseñar un logo atractivo para tu proyecto personal como desarrollador, desde la elección de colores hasta el uso de herramientas gratuitas.",
  "tags": [
    "logos",
    "branding",
    "desarrolladores",
    "diseño",
    "herramientas",
    "proyectos personales"
  ],
  "content": "<h1>Cómo los desarrolladores pueden crear logos efectivos para sus proyectos personales</h1><p>Los logos son una parte crucial de la identidad visual...</p>",
  "created_at": "2024-12-19",
  "updated_at": null,
  "author": "Nombre del autor",
  "image_url": "https://unsplash.com/photos/xyz123",
  "cta": {
    "text": "¡Prueba nuestra herramienta para crear logos ahora!",
    "url": "https://tuherramienta.com"
  }
}
